MANIFEST.in
bootstrap.py
buildout.cfg
readme.txt
setup.py
version.txt
mirror/__init__.py
mirror.pfg.egg-info/PKG-INFO
mirror.pfg.egg-info/SOURCES.txt
mirror.pfg.egg-info/dependency_links.txt
mirror.pfg.egg-info/namespace_packages.txt
mirror.pfg.egg-info/not-zip-safe
mirror.pfg.egg-info/requires.txt
mirror.pfg.egg-info/top_level.txt
mirror/pfg/__init__.py
mirror/pfg/configure.zcml
mirror/pfg/interfaces.py
mirror/pfg/readme.txt
mirror/pfg/tests.py
mirror/pfg/transform.py