Metadata-Version: 1.0
Name: mirror.pfg
Version: 0.2.2
Summary: Extension for Content Mirror to Support Plone Form Gen
Home-page: http://contentmirror.googlecode.com
Author: Tim Knapp
Author-email: UNKNOWN
License: GPL
Keywords: plone
Platform: UNKNOWN
